apportionpy/__init__.py
apportionpy/apportionment.py
apportionpy/experimental/__init__.py
apportionpy/experimental/boundary.py
apportionpy/methods/__init__.py
apportionpy/methods/adam.py
apportionpy/methods/equal_proportions.py
apportionpy/methods/hamilton.py
apportionpy/methods/huntington_hill.py
apportionpy/methods/jefferson.py
apportionpy/methods/webster.py
apportionpy-0.3.1.dist-info/LICENSE.TXT
apportionpy-0.3.1.dist-info/METADATA
apportionpy-0.3.1.dist-info/WHEEL
apportionpy-0.3.1.dist-info/top_level.txt
apportionpy-0.3.1.dist-info/RECORD
