Metadata-Version: 2.1
Name: apportionpy
Version: 0.3.1
Summary: A Python package for apportionment.
Home-page: UNKNOWN
Author: Brandon Rorie
Author-email: ticer1999@gmail.com
License: UNKNOWN
Keywords: python,apportionment,apportion,hamilton,webster,adam,jefferson,Huntington,method,equal,proportions
Platform: UNKNOWN
Classifier: Development Status :: 1 - Planning
Classifier: Intended Audience :: Developers
Classifier: Programming Language :: Python :: 3
Classifier: Operating System :: Unix
Classifier: Operating System :: MacOS :: MacOS X
Classifier: Operating System :: Microsoft :: Windows
License-File: LICENSE.TXT
